pycardano/__init__.py
pycardano/address.py
pycardano/backend/__init__.py
pycardano/backend/base.py
pycardano/backend/blockfrost.py
pycardano/backend/cardano_cli.py
pycardano/backend/kupo.py
pycardano/backend/ogmios_v5.py
pycardano/backend/ogmios_v6.py
pycardano/cbor.py
pycardano/certificate.py
pycardano/cip/__init__.py
pycardano/cip/cip14.py
pycardano/cip/cip8.py
pycardano/coinselection.py
pycardano/crypto/__init__.py
pycardano/crypto/bech32.py
pycardano/crypto/bip32.py
pycardano/exception.py
pycardano/governance.py
pycardano/hash.py
pycardano/key.py
pycardano/logging.py
pycardano/metadata.py
pycardano/nativescript.py
pycardano/network.py
pycardano/plutus.py
pycardano/pool_params.py
pycardano/serialization.py
pycardano/transaction.py
pycardano/txbuilder.py
pycardano/types.py
pycardano/utils.py
pycardano/witness.py
pycardano-0.19.0.dist-info/METADATA
pycardano-0.19.0.dist-info/WHEEL
pycardano-0.19.0.dist-info/licenses/LICENSE
pycardano-0.19.0.dist-info/RECORD
