Metadata-Version: 2.4
Name: pycardano
Version: 0.19.0
Summary: A Cardano library in Python
License: MIT
License-File: LICENSE
Keywords: python,cardano,blockchain,crypto
Author: Jerry
Author-email: jerrycgh@gmail.com
Requires-Python: >=3.9.1,<4.0.0
Classifier: Intended Audience :: Developers
Classifier: License :: OSI Approved :: MIT License
Classifier: Natural Language :: English
Classifier: Programming Language :: Python :: 3
Classifier: Programming Language :: Python :: 3.10
Classifier: Programming Language :: Python :: 3.11
Classifier: Programming Language :: Python :: 3.12
Classifier: Programming Language :: Python :: 3.13
Classifier: Programming Language :: Python :: 3.14
Classifier: Programming Language :: Python :: 3.9
Requires-Dist: ECPy (>=1.2.5)
Requires-Dist: PyNaCl (>=1.5.0)
Requires-Dist: base58 (>=2.1.0)
Requires-Dist: blockfrost-python (>=0.6.0)
Requires-Dist: cachetools (>=5.3.0)
Requires-Dist: cbor2 (>=5.6.5)
Requires-Dist: cbor2pure (>=5.7.2)
Requires-Dist: cose (>=0.9.dev8)
Requires-Dist: docker (>=7.1.0)
Requires-Dist: frozendict (>=2.3.8)
Requires-Dist: frozenlist (>=1.3.3)
Requires-Dist: mnemonic (>=0.21)
Requires-Dist: ogmios (>=1.4.2)
Requires-Dist: pprintpp (>=0.4.0)
Requires-Dist: requests (>=2.32.3)
Requires-Dist: typeguard (>=4.3.0)
Requires-Dist: websocket-client (>=1.4.1)
Requires-Dist: websockets (>=13.0)
Project-URL: Documentation, https://pycardano.readthedocs.io/en/latest/
Project-URL: Homepage, https://github.com/Python-Cardano/pycardano
Project-URL: Repository, https://github.com/Python-Cardano/pycardano
